pymosp/__init__.py
pymosp/api.py
pymosp/exceptions.py
pymosp/mospobject.py
pymosp/py.typed
pymosp-0.5.3.dist-info/AUTHORS.md
pymosp-0.5.3.dist-info/COPYING
pymosp-0.5.3.dist-info/METADATA
pymosp-0.5.3.dist-info/WHEEL
pymosp-0.5.3.dist-info/entry_points.txt
pymosp-0.5.3.dist-info/RECORD
