Metadata-Version: 2.3
Name: PyMOSP
Version: 0.5.3
Summary: Python Library to access MOSP.
License: GPL-3.0-or-later
Keywords: json,mosp,security
Author: Cédric Bonhomme
Author-email: cedric@cedricbonhomme.org
Requires-Python: >=3.10,<4.0
Classifier: Development Status :: 5 - Production/Stable
Classifier: Environment :: Console
Classifier: Intended Audience :: Information Technology
Classifier: License :: OSI Approved :: GNU General Public License v3 or later (GPLv3+)
Classifier: Operating System :: POSIX :: Linux
Classifier: Programming Language :: Python :: 3
Classifier: Programming Language :: Python :: 3.10
Classifier: Programming Language :: Python :: 3.11
Classifier: Programming Language :: Python :: 3.12
Classifier: Programming Language :: Python :: 3.13
Classifier: Programming Language :: Python :: 3.9
Classifier: Topic :: Internet
Classifier: Topic :: Security
Requires-Dist: mypy (>=1.15.0)
Requires-Dist: requests (>=2.32.3)
Requires-Dist: types-requests (>=2.32.0.20241016)
Project-URL: Changelog, https://github.com/NC3-LU/PyMOSP/blob/master/CHANGELOG.md
Project-URL: Homepage, https://github.com/NC3-LU/PyMOSP
Project-URL: Repository, https://github.com/NC3-LU/PyMOSP
